Metadata-Version: 2.1
Name: apscrypt
Version: 0.0.1
Summary: The easy-to-use crypter.
Home-page: https://github.com/Sellig6792/APSCrypt
Author: Sellig6792
License: LICENSE
Platform: UNKNOWN
Classifier: Programming Language :: Python :: 3
Classifier: License :: OSI Approved :: MIT License
Classifier: Operating System :: OS Independent
Requires-Python: >=3.6
License-File: LICENSE
